ehlek/__init__.py
ehlek/fn.py
ehlek-0.2.1.dist-info/METADATA
ehlek-0.2.1.dist-info/WHEEL
ehlek-0.2.1.dist-info/top_level.txt
ehlek-0.2.1.dist-info/RECORD
