Metadata-Version: 2.1
Name: ehlek
Version: 0.2.1
Requires-Dist: numpy
Requires-Dist: pandas
Requires-Dist: ccxt
Requires-Dist: ta
Requires-Dist: pytz
